kpireport_twitter/__init__.py
kpireport_twitter/datasource.py
kpireport_twitter/engagement.py
kpireport_twitter-0.1.1.dist-info/METADATA
kpireport_twitter-0.1.1.dist-info/WHEEL
kpireport_twitter-0.1.1.dist-info/entry_points.txt
kpireport_twitter-0.1.1.dist-info/top_level.txt
kpireport_twitter-0.1.1.dist-info/RECORD
