Metadata-Version: 2.1
Name: kpireport-twitter
Version: 0.1.1
Summary: A Twitter datasource for KPI Reporter
Home-page: https://kpireporter.com
Author: KPI Reporter LLC
Author-email: dev@kpireporter.com
License: Prosperity Public License
Platform: UNKNOWN
Requires-Dist: kpireport
Requires-Dist: kpireport-plot
Requires-Dist: TwitterAPI
